django_thrift/__init__.py
django_thrift/apps.py
django_thrift/file.py
django_thrift/handler.py
django_thrift/models.py
django_thrift/tests.py
django_thrift/management/__init__.py
django_thrift/management/commands/__init__.py
django_thrift/management/commands/runrpcserver.py
django_thrift/migrations/__init__.py
django_thrift/server/__init__.py
django_thrift/server/rpc.py
django_thrift-0.1.3.dist-info/DESCRIPTION.rst
django_thrift-0.1.3.dist-info/METADATA
django_thrift-0.1.3.dist-info/RECORD
django_thrift-0.1.3.dist-info/WHEEL
django_thrift-0.1.3.dist-info/metadata.json
django_thrift-0.1.3.dist-info/top_level.txt
