Metadata-Version: 2.0
Name: django-thrift
Version: 0.1.3
Summary: Django App to Run a Apache Thrift RPC Server
Home-page: https://github.com/dstarner15/django_thrift
Author: Daniel Starner
Author-email: starner.daniel5@gmail.com
License: UNKNOWN
Platform: UNKNOWN
Classifier: Development Status :: 4 - Beta
Classifier: Environment :: Web Environment
Classifier: Framework :: Django
Classifier: Framework :: Django :: 1.8
Classifier: Framework :: Django :: 1.9
Classifier: Framework :: Django :: 1.10
Classifier: Framework :: Django :: 1.11
Classifier: Operating System :: OS Independent
Classifier: Programming Language :: Python
Classifier: Programming Language :: Python :: 2
Classifier: Programming Language :: Python :: 2.7
Classifier: Programming Language :: Python :: 3
Classifier: Programming Language :: Python :: 3.4
Classifier: Programming Language :: Python :: 3.5
Classifier: Programming Language :: Python :: 3.6
Requires-Dist: django
Requires-Dist: gunicorn-thrift
Requires-Dist: pytz
Requires-Dist: thrift
Requires-Dist: thriftpy
